{
  "name": "demo level",
  "width": 2000,
  "height": 2000,
  "playerStartPosX": 1000,
  "playerStartPosY": 300,
  "timeLimitInSeconds": 25,
  "boundaryPoints": [
    { "x": 100, "y": 100 },
    { "x": 1900, "y": 100 },
    { "x": 1900, "y": 2000 },
    { "x": 100, "y": 2000 }
  ],
  "objects": [
    {
      "x": 1600,
      "y": 1600,
      "points": [
        { "x": -100, "y": -100 },
        { "x": 100, "y": -100 },
        { "x": 100, "y": 100 },
        { "x": -100, "y": 100 }
      ]
    },
    {
      "x": 400,
      "y": 400,
      "points": [
        { "x": -100, "y": -100 },
        { "x": 100, "y": -100 },
        { "x": 100, "y": 100 },
        { "x": -100, "y": 100 }
      ]
    }

  ],
  "targets": [
    { "x": 1000, "y": 1000 }
  ]
}
